Config.py
FlushStreamHandler.py
MlModelGenerator.py
PipesimInputGenerator.py
PipesimRunner.py
Runner.py
TimerService.py
tmnsokol727272-0.1.0.dist-info/METADATA
tmnsokol727272-0.1.0.dist-info/WHEEL
tmnsokol727272-0.1.0.dist-info/top_level.txt
tmnsokol727272-0.1.0.dist-info/RECORD
