Metadata-Version: 2.4
Name: tmnsokol727272
Version: 0.1.0
Summary: test description
Author-email: Sergei Sokol <you@example.com>
Project-URL: Homepage, http://www.slb.com
Classifier: Programming Language :: Python :: 3
Classifier: License :: OSI Approved :: MIT License
Classifier: Operating System :: OS Independent
Requires-Python: >=3.12
